deadpad/__init__.py
deadpad/extensions/python/__init__.py
deadpad/parts/__init__.py
deadpad/parts/document.py
deadpad/parts/extension.py
deadpad/parts/input_handler.py
deadpad/parts/keys.py
deadpad/parts/linux_input.py
deadpad/parts/textscreen.py
deadpad/parts/themes.py
deadpad/parts/windows_input.py
deadpad/themes/default.json
preview/DeadPad1.gif
preview/deadpad2.gif
deadpad-0.2.3.dist-info/LICENSE
deadpad-0.2.3.dist-info/METADATA
deadpad-0.2.3.dist-info/WHEEL
deadpad-0.2.3.dist-info/entry_points.txt
deadpad-0.2.3.dist-info/top_level.txt
deadpad-0.2.3.dist-info/RECORD
