Metadata-Version: 2.1
Name: deadpad
Version: 0.2.3
Summary: A customizeable lightweight CLI/TUI text editor made without curses or any TUI framework.
Author: William L.
Project-URL: Homepage, https://github.com/FrewtyPebbles/DeadPad-CLI-Text-Editor
Project-URL: Issues, https://github.com/FrewtyPebbles/DeadPad-CLI-Text-Editor/issues
Classifier: Programming Language :: Python :: 3
Classifier: License :: OSI Approved :: MIT License
Classifier: Operating System :: OS Independent
Requires-Python: >=3.10
License-File: LICENSE
